.DS_Store
LICENSE.txt
MANIFEST
MANIFEST.in
README.md
setup.cfg
setup.py
rlsimple/.DS_Store
rlsimple/.gitignore
rlsimple/CNN.py
rlsimple/CNN.pyc
rlsimple/GameEngine.py
rlsimple/GameEngine.pyc
rlsimple/NN.py
rlsimple/NN.pyc
rlsimple/__init__.py
rlsimple/__init__.pyc
rlsimple/test.gv
rlsimple/test.gv.png
rlsimple.egg-info/PKG-INFO
rlsimple.egg-info/SOURCES.txt
rlsimple.egg-info/dependency_links.txt
rlsimple.egg-info/top_level.txt
rlsimple/.idea/misc.xml
rlsimple/.idea/modules.xml
rlsimple/.idea/rlsimple.iml
rlsimple/.idea/vcs.xml
rlsimple/.idea/workspace.xml
rlsimple/.idea/inspectionProfiles/Project_Default.xml
rlsimple/.idea/inspectionProfiles/profiles_settings.xml
rlsimple/DDPG/Actor.py
rlsimple/DDPG/Actor.pyc
rlsimple/DDPG/Critic.py
rlsimple/DDPG/Critic.pyc
rlsimple/DDPG/DDPG.py
rlsimple/DDPG/ReplayBuffer.py
rlsimple/DDPG/ReplayBuffer.pyc
rlsimple/DDPG/__init__.py
rlsimple/DDPG/.idea/DDPG.iml
rlsimple/DDPG/.idea/misc.xml
rlsimple/DDPG/.idea/modules.xml
rlsimple/DDPG/.idea/vcs.xml
rlsimple/DDPG/.idea/workspace.xml
rlsimple/DDPG/.idea/inspectionProfiles/Project_Default.xml
rlsimple/DDPG/.idea/inspectionProfiles/profiles_settings.xml
rlsimple/DQN/DQN.py
rlsimple/DQN/__init__.py
rlsimple/DQN/deep_q_network.py
rlsimple/FlappyBirdEnv/__init__.py
rlsimple/FlappyBirdEnv/__init__.pyc
rlsimple/FlappyBirdEnv/flappy_bird_utils.py
rlsimple/FlappyBirdEnv/flappy_bird_utils.pyc
rlsimple/FlappyBirdEnv/wrapped_flappy_bird.py
rlsimple/FlappyBirdEnv/wrapped_flappy_bird.pyc
rlsimple/FlappyBirdEnv/assets/audio/die.ogg
rlsimple/FlappyBirdEnv/assets/audio/die.wav
rlsimple/FlappyBirdEnv/assets/audio/hit.ogg
rlsimple/FlappyBirdEnv/assets/audio/hit.wav
rlsimple/FlappyBirdEnv/assets/audio/point.ogg
rlsimple/FlappyBirdEnv/assets/audio/point.wav
rlsimple/FlappyBirdEnv/assets/audio/swoosh.ogg
rlsimple/FlappyBirdEnv/assets/audio/swoosh.wav
rlsimple/FlappyBirdEnv/assets/audio/wing.ogg
rlsimple/FlappyBirdEnv/assets/audio/wing.wav
rlsimple/FlappyBirdEnv/assets/sprites/0.png
rlsimple/FlappyBirdEnv/assets/sprites/1.png
rlsimple/FlappyBirdEnv/assets/sprites/2.png
rlsimple/FlappyBirdEnv/assets/sprites/3.png
