Metadata-Version: 1.1
Name: rlsimple
Version: 1.1
Summary: reinforcement learning simple library
Home-page: https://github.com/rabbitnoname/rlsimple
Author: Rabbit Noname
Author-email: faithoptimistic@gmail.com
License: UNKNOWN
Download-URL: https://github.com/rabbitnoname/rlsimple/archive/master.zip
Keywords: reinforcement learning,DDPG,DQN,Actor Critic,simple library
Platform: UNKNOWN
Classifier: Development Status :: 3 - Alpha
Classifier: Intended Audience :: Developers
Classifier: Topic :: Software Development :: Build Tools
Classifier: License :: OSI Approved :: MIT License
Classifier: Programming Language :: Python :: 2.7
